aiocloudweather/__init__.py
aiocloudweather/__main__.py
aiocloudweather/const.py
aiocloudweather/conversion.py
aiocloudweather/proxy.py
aiocloudweather/py.typed
aiocloudweather/server.py
aiocloudweather/station.py
aiocloudweather-2024.12.2.dist-info/LICENSE
aiocloudweather-2024.12.2.dist-info/METADATA
aiocloudweather-2024.12.2.dist-info/WHEEL
aiocloudweather-2024.12.2.dist-info/entry_points.txt
aiocloudweather-2024.12.2.dist-info/top_level.txt
aiocloudweather-2024.12.2.dist-info/RECORD
